gdpr_assist/__init__.py
gdpr_assist/anonymiser.py
gdpr_assist/app_settings.py
gdpr_assist/apps.py
gdpr_assist/cast.py
gdpr_assist/deletion.py
gdpr_assist/exceptions.py
gdpr_assist/handlers.py
gdpr_assist/models.py
gdpr_assist/registry.py
gdpr_assist/routers.py
gdpr_assist/signals.py
gdpr_assist/upgrading.py
gdpr_assist/admin/__init__.py
gdpr_assist/admin/base.py
gdpr_assist/admin/tool.py
gdpr_assist/management/__init__.py
gdpr_assist/management/commands/__init__.py
gdpr_assist/management/commands/anonymise_db.py
gdpr_assist/management/commands/gdpr_rerun.py
gdpr_assist/migrations/0001_initial.py
gdpr_assist/migrations/0002_privacyanonymised.py
gdpr_assist/migrations/0003_auto_20210205_1657.py
gdpr_assist/migrations/0004_auto_20211215_1057.py
gdpr_assist/migrations/__init__.py
gdpr_assist/templates/gdpr_assist/admin/action_anonymise.html
gdpr_assist/templates/gdpr_assist/admin/pd_change_list.html
django_gdpr_assist-1.4.2.dist-info/LICENSE
django_gdpr_assist-1.4.2.dist-info/METADATA
django_gdpr_assist-1.4.2.dist-info/WHEEL
django_gdpr_assist-1.4.2.dist-info/top_level.txt
django_gdpr_assist-1.4.2.dist-info/zip-safe
django_gdpr_assist-1.4.2.dist-info/RECORD
