Metadata-Version: 2.1
Name: django-gdpr-assist
Version: 1.4.2
Summary: GDPR tools for Django sites
Home-page: https://github.com/wildfish/django-gdpr-assist
Author: Wildfish
Author-email: developers@wildfish.com
License: BSD
Keywords: django gdpr
Platform: UNKNOWN
Classifier: Development Status :: 5 - Production/Stable
Classifier: Environment :: Web Environment
Classifier: Intended Audience :: Developers
Classifier: License :: OSI Approved :: BSD License
Classifier: Operating System :: OS Independent
Classifier: Programming Language :: Python :: 3
Classifier: Programming Language :: Python :: 3.5
Classifier: Programming Language :: Python :: 3.6
Classifier: Programming Language :: Python :: 3.7
Classifier: Programming Language :: Python :: 3.8
Classifier: Programming Language :: Python :: 3.9
Classifier: Framework :: Django
Classifier: Framework :: Django :: 2.2
Classifier: Framework :: Django :: 3.0
Classifier: Framework :: Django :: 3.1
Classifier: Framework :: Django :: 3.2
License-File: LICENSE
Requires-Dist: django-yaa-settings (>=1.1)
Provides-Extra: dev
Requires-Dist: tox ; extra == 'dev'
Requires-Dist: pillow ; extra == 'dev'
Requires-Dist: model-bakery ; extra == 'dev'
Requires-Dist: freezegun ; extra == 'dev'
Requires-Dist: sphinx ; extra == 'dev'
Requires-Dist: sphinx-autobuild ; extra == 'dev'
Requires-Dist: sphinx-rtd-theme ; extra == 'dev'
